bazis/contrib/ws/__init__.py
bazis/contrib/ws/_version.py
bazis/contrib/ws/models_abstract.py
bazis/contrib/ws/routes_abstract.py
bazis/contrib/ws/utils.py
bazis/contrib/ws/ws.py
bazis_ws-2.2.1.dist-info/METADATA
bazis_ws-2.2.1.dist-info/WHEEL
bazis_ws-2.2.1.dist-info/top_level.txt
bazis_ws-2.2.1.dist-info/RECORD
