Metadata-Version: 2.4
Name: bazis-ws
Version: 2.2.1
Summary: WebSocket module for Bazis framework.
Author-email: Ilya Kharyn <ilya.tt07@gmail.com>
Maintainer-email: Ilya Kharyn <ilya.tt07@gmail.com>
Project-URL: Home, https://github.com/ecofuture-tech/bazis-ws
Keywords: bazis,django,fastapi,pydantic,framework,jsonapi,websocket
Classifier: Intended Audience :: Developers
Classifier: Topic :: Software Development :: Libraries :: Python Modules
Classifier: Operating System :: OS Independent
Classifier: Programming Language :: Python :: 3
Classifier: Programming Language :: Python :: 3.12
Classifier: Programming Language :: Python :: 3.13
Classifier: Programming Language :: Python :: 3.14
Classifier: Framework :: Django
Classifier: Framework :: FastAPI
Requires-Python: >=3.12
Requires-Dist: bazis
Provides-Extra: test
Requires-Dist: bazis-test-utils; extra == "test"
Provides-Extra: dev
Requires-Dist: ruff; extra == "dev"
